scrape_eazy/__init__.py
scrape_eazy/core.py
scrape_eazy/utils.py
scrape_eazy-0.1.0.dist-info/METADATA
scrape_eazy-0.1.0.dist-info/WHEEL
scrape_eazy-0.1.0.dist-info/top_level.txt
scrape_eazy-0.1.0.dist-info/RECORD
