Metadata-Version: 2.4
Name: scrape_eazy
Version: 0.1.0
Summary: A simple web scraping helper for humans
Author-email: Your Name <you@example.com>
License: MIT
Requires-Python: >=3.8
Requires-Dist: requests
Requires-Dist: beautifulsoup4
